fragmentcolor-0.10.10.dist-info/METADATA
fragmentcolor-0.10.10.dist-info/WHEEL
fragmentcolor-0.10.10.dist-info/licenses/LICENSE.md
fragmentcolor/__init__.py
fragmentcolor/fragmentcolor.pyd
fragmentcolor-0.10.10.dist-info/RECORD
