Metadata-Version: 2.4
Name: fragmentcolor
Version: 0.10.10
Classifier: Development Status :: 2 - Pre-Alpha
Classifier: Programming Language :: Rust
Classifier: Environment :: GPU
Classifier: Intended Audience :: Developers
Classifier: License :: OSI Approved :: MIT License
Classifier: Operating System :: OS Independent
Classifier: Topic :: Multimedia :: Graphics
Classifier: Topic :: Multimedia :: Graphics :: 3D Rendering
Requires-Dist: rendercanvas
Requires-Dist: gltf
Requires-Dist: pytest<5.0.0 ; extra == 'test'
Requires-Dist: pytest-cov[all] ; extra == 'test'
Provides-Extra: test
License-File: LICENSE.md
Summary: Easy cross-platform GPU Rendering for Javascript, Python, Swift and Kotlin
Keywords: graphics,rendering,wgpu,cross-platform,art
Home-Page: https://fragmentcolor.org
Author: Rafael Beckel
Maintainer: Rafael Beckel
License-Expression: MIT
Requires-Python: >=3.9
Project-URL: homepage, https://fragmentcolor.org
Project-URL: documentation, https://fragmentcolor.org/welcome
Project-URL: repository, https://github.com/vista-art/fragmentcolor
Project-URL: changelog, https://github.com/vista-art/fragmentcolor/releases
